LICENSE.txt
README.md
setup.cfg
jsrl_library_common/__init__.py
jsrl_library_common/constants/__init__.py
jsrl_library_common/constants/database/__init__.py
jsrl_library_common/constants/database/athena_constants.py
jsrl_library_common/constants/database/engines.py
jsrl_library_common/exceptions/__init__.py
jsrl_library_common/exceptions/database/__init__.py
jsrl_library_common/exceptions/database/athena_exceptions.py
jsrl_library_common/models/__init__.py
jsrl_library_common/models/database/__init__.py
jsrl_library_common/models/database/athena_conn_model.py
jsrl_library_common/models/database/database_engine_conf_model.py
jsrl_library_common/utils/__init__.py
jsrl_library_common/utils/aws/__init__.py
jsrl_library_common/utils/aws/athena_database.py
jsrl_library_common/utils/database/__init__.py
jsrl_library_common/utils/database/athena.py
jsrl_library_common/utils/decorators/__init__.py
jsrl_library_common/utils/decorators/query_connection.py
jsrl_library_common_athena_database-0.0.1.dist-info/licenses/LICENSE.txt
jsrl_library_common_athena_database.egg-info/PKG-INFO
jsrl_library_common_athena_database.egg-info/SOURCES.txt
jsrl_library_common_athena_database.egg-info/dependency_links.txt
jsrl_library_common_athena_database.egg-info/requires.txt
jsrl_library_common_athena_database.egg-info/top_level.txt
tests/test_database_engine_recognition.py
tests/test_send_athena_query.py
jsrl_library_common_athena_database-0.0.1.dist-info/METADATA
jsrl_library_common_athena_database-0.0.1.dist-info/WHEEL
jsrl_library_common_athena_database-0.0.1.dist-info/top_level.txt
jsrl_library_common_athena_database-0.0.1.dist-info/RECORD
